Workbook

Sheet Financial Report
A1: Financial Reports
A2: ='Setup & Guide'!$B$3&" | "&'Setup & Guide'!$B$4 -> Rulership LTD PTY | 2L Detergent Manufacturing & Retail Sales | F2: ='Setup & Guide'!$B$5 -> Sakhile Ext7 Facility
A3: Formula-driven monthly inventory and sales performance | F3: ='Setup & Guide'!$B$6 -> 46235
A5: TOTAL MONTHLY GROSS REVENUE | C5: SARS VAT COLLECTED | E5: PRODUCT GROSS MARGIN ✓
A6: =SUM('System Data'!$K$6:$K$55) -> 140679.9 | C6: =SUM('System Data'!$L$6:$L$55) -> 21101.99 | E6: =IFERROR(SUM('System Data'!$M$6:$M$55)/SUM('System Data'!$K$6:$K$55),0) -> 0.41174134
A8: Growth vs previous month | B8: =IFERROR((A6-'Setup & Guide'!$B$8)/'Setup & Guide'!$B$8,0) -> 0.14200003 | C8: South African Revenue Service output tax | E8: Weighted average unit price | G8: =IFERROR(SUM('System Data'!$K$6:$K$55)/SUM('System Data'!$G$6:$G$55),0) -> 69.99
A10: Product Revenue Breakdown | F10: ='Setup & Guide'!$B$5 -> Sakhile Ext7 Facility
A11: PRODUCT | B11: UNITS SOLD | C11: UNIT PRICE (ZAR) | D11: REVENUE (ZAR) | E11: 15% VAT (ZAR) | F11: CLOSING STOCK | G11: GROSS MARGIN %
A12: =IF('System Data'!$B6="","",'System Data'!$B6) -> 2L Dish Washing Liquid | B12: =IF($A12="","",'System Data'!$G6) -> 840 | C12: =IF($A12="","",'System Data'!$I6) -> 69.99 | D12: =IF($A12="","",'System Data'!$K6) -> 58791.6 | E12: =IF($A12="","",'System Data'!$L6) -> 8818.74 | F12: =IF($A12="","",'System Data'!$O6) -> 200 | G12: =IF($A12="","",'System Data'!$N6) -> 0.425
A13: =IF('System Data'!$B7="","",'System Data'!$B7) -> 2L Pine Gel Concentrated Cleaner | B13: =IF($A13="","",'System Data'!$G7) -> 650 | C13: =IF($A13="","",'System Data'!$I7) -> 69.99 | D13: =IF($A13="","",'System Data'!$K7) -> 45493.5 | E13: =IF($A13="","",'System Data'!$L7) -> 6824.03 | F13: =IF($A13="","",'System Data'!$O7) -> 100 | G13: =IF($A13="","",'System Data'!$N7) -> 0.40800004
A14: =IF('System Data'!$B8="","",'System Data'!$B8) -> 2L Multi-Purpose Surface Cleaner | B14: =IF($A14="","",'System Data'!$G8) -> 520 | C14: =IF($A14="","",'System Data'!$I8) -> 69.99 | D14: =IF($A14="","",'System Data'!$K8) -> 36394.8 | E14: =IF($A14="","",'System Data'!$L8) -> 5459.22 | F14: =IF($A14="","",'System Data'!$O8) -> 80 | G14: =IF($A14="","",'System Data'!$N8) -> 0.39500011
A15: =IF('System Data'!$B9="","",'System Data'!$B9) | B15: =IF($A15="","",'System Data'!$G9) | C15: =IF($A15="","",'System Data'!$I9) | D15: =IF($A15="","",'System Data'!$K9) | E15: =IF($A15="","",'System Data'!$L9) | F15: =IF($A15="","",'System Data'!$O9) | G15: =IF($A15="","",'System Data'!$N9)
A16: =IF('System Data'!$B10="","",'System Data'!$B10) | B16: =IF($A16="","",'System Data'!$G10) | C16: =IF($A16="","",'System Data'!$I10) | D16: =IF($A16="","",'System Data'!$K10) | E16: =IF($A16="","",'System Data'!$L10) | F16: =IF($A16="","",'System Data'!$O10) | G16: =IF($A16="","",'System Data'!$N10)
A17: =IF('System Data'!$B11="","",'System Data'!$B11) | B17: =IF($A17="","",'System Data'!$G11) | C17: =IF($A17="","",'System Data'!$I11) | D17: =IF($A17="","",'System Data'!$K11) | E17: =IF($A17="","",'System Data'!$L11) | F17: =IF($A17="","",'System Data'!$O11) | G17: =IF($A17="","",'System Data'!$N11)
A18: =IF('System Data'!$B12="","",'System Data'!$B12) | B18: =IF($A18="","",'System Data'!$G12) | C18: =IF($A18="","",'System Data'!$I12) | D18: =IF($A18="","",'System Data'!$K12) | E18: =IF($A18="","",'System Data'!$L12) | F18: =IF($A18="","",'System Data'!$O12) | G18: =IF($A18="","",'System Data'!$N12)
A19: =IF('System Data'!$B13="","",'System Data'!$B13) | B19: =IF($A19="","",'System Data'!$G13) | C19: =IF($A19="","",'System Data'!$I13) | D19: =IF($A19="","",'System Data'!$K13) | E19: =IF($A19="","",'System Data'!$L13) | F19: =IF($A19="","",'System Data'!$O13) | G19: =IF($A19="","",'System Data'!$N13)
A20: =IF('System Data'!$B14="","",'System Data'!$B14) | B20: =IF($A20="","",'System Data'!$G14) | C20: =IF($A20="","",'System Data'!$I14) | D20: =IF($A20="","",'System Data'!$K14) | E20: =IF($A20="","",'System Data'!$L14) | F20: =IF($A20="","",'System Data'!$O14) | G20: =IF($A20="","",'System Data'!$N14)
A21: =IF('System Data'!$B15="","",'System Data'!$B15) | B21: =IF($A21="","",'System Data'!$G15) | C21: =IF($A21="","",'System Data'!$I15) | D21: =IF($A21="","",'System Data'!$K15) | E21: =IF($A21="","",'System Data'!$L15) | F21: =IF($A21="","",'System Data'!$O15) | G21: =IF($A21="","",'System Data'!$N15)
A22: =IF('System Data'!$B16="","",'System Data'!$B16) | B22: =IF($A22="","",'System Data'!$G16) | C22: =IF($A22="","",'System Data'!$I16) | D22: =IF($A22="","",'System Data'!$K16) | E22: =IF($A22="","",'System Data'!$L16) | F22: =IF($A22="","",'System Data'!$O16) | G22: =IF($A22="","",'System Data'!$N16)
A23: =IF('System Data'!$B17="","",'System Data'!$B17) | B23: =IF($A23="","",'System Data'!$G17) | C23: =IF($A23="","",'System Data'!$I17) | D23: =IF($A23="","",'System Data'!$K17) | E23: =IF($A23="","",'System Data'!$L17) | F23: =IF($A23="","",'System Data'!$O17) | G23: =IF($A23="","",'System Data'!$N17)
... A61: =IF('System Data'!$B55="","",'System Data'!$B55) | B61: =IF($A61="","",'System Data'!$G55) | C61: =IF($A61="","",'System Data'!$I55) | D61: =IF($A61="","",'System Data'!$K55) | E61: =IF($A61="","",'System Data'!$L55) | F61: =IF($A61="","",'System Data'!$O55) | G61: =IF($A61="","",'System Data'!$N55)
A62: TOTAL | B62: =SUM(B12:B61) -> 2010 | D62: =SUM(D12:D61) -> 140679.9 | E62: =SUM(E12:E61) -> 21101.99 | F62: =SUM(F12:F61) -> 380 | G62: =IFERROR(SUM('System Data'!$M$6:$M$55)/D62,0) -> 0.41174134
A64: Template note: VAT is calculated as revenue × the configured VAT rate, matching the supplied report design. Unit prices are treated as VAT-exclusive.

Sheet System Data
A1: SYSTEM DATA INPUT
A2: Your system should write only to blue columns A:J. Columns K:O calculate automatically.
A4: INPUT FIELDS | K4: CALCULATED FIELDS - DO NOT OVERWRITE
A5: SKU | B5: Product Name | C5: Category / Product Line | D5: Unit Label | E5: Opening Stock | F5: Units Manufactured | G5: Units Sold | H5: Stock Adjustments | I5: Unit Price (ZAR) | J5: Unit Cost (ZAR) | K5: Revenue (ZAR) | L5: VAT (ZAR) | M5: Gross Profit (ZAR) | N5: Gross Margin % | O5: Closing Stock
A6: 2L-DWL | B6: 2L Dish Washing Liquid | C6: 2L Detergent Line | D6: bottles | E6: 240 | F6: 800 | G6: 840 | H6: 0 | I6: 69.99 | J6: 40.24425 | K6: =IF(B6="","",ROUND(G6*I6,2)) -> 58791.6 | L6: =IF(B6="","",ROUND(K6*'Setup & Guide'!$B$7,2)) -> 8818.74 | M6: =IF(B6="","",ROUND(K6-(G6*J6),2)) -> 24986.43 | N6: =IF(B6="","",IFERROR(M6/K6,0)) -> 0.425 | O6: =IF(B6="","",E6+F6+H6-G6) -> 200
A7: 2L-PGC | B7: 2L Pine Gel Concentrated Cleaner | C7: 2L Detergent Line | D7: bottles | E7: 150 | F7: 600 | G7: 650 | H7: 0 | I7: 69.99 | J7: 41.43408 | K7: =IF(B7="","",ROUND(G7*I7,2)) -> 45493.5 | L7: =IF(B7="","",ROUND(K7*'Setup & Guide'!$B$7,2)) -> 6824.03 | M7: =IF(B7="","",ROUND(K7-(G7*J7),2)) -> 18561.35 | N7: =IF(B7="","",IFERROR(M7/K7,0)) -> 0.40800004 | O7: =IF(B7="","",E7+F7+H7-G7) -> 100
A8: 2L-MPC | B8: 2L Multi-Purpose Surface Cleaner | C8: 2L Detergent Line | D8: bottles | E8: 100 | F8: 500 | G8: 520 | H8: 0 | I8: 69.99 | J8: 42.34395 | K8: =IF(B8="","",ROUND(G8*I8,2)) -> 36394.8 | L8: =IF(B8="","",ROUND(K8*'Setup & Guide'!$B$7,2)) -> 5459.22 | M8: =IF(B8="","",ROUND(K8-(G8*J8),2)) -> 14375.95 | N8: =IF(B8="","",IFERROR(M8/K8,0)) -> 0.39500011 | O8: =IF(B8="","",E8+F8+H8-G8) -> 80
K9: =IF(B9="","",ROUND(G9*I9,2)) | L9: =IF(B9="","",ROUND(K9*'Setup & Guide'!$B$7,2)) | M9: =IF(B9="","",ROUND(K9-(G9*J9),2)) | N9: =IF(B9="","",IFERROR(M9/K9,0)) | O9: =IF(B9="","",E9+F9+H9-G9)
K10: =IF(B10="","",ROUND(G10*I10,2)) | L10: =IF(B10="","",ROUND(K10*'Setup & Guide'!$B$7,2)) | M10: =IF(B10="","",ROUND(K10-(G10*J10),2)) | N10: =IF(B10="","",IFERROR(M10/K10,0)) | O10: =IF(B10="","",E10+F10+H10-G10)
K11: =IF(B11="","",ROUND(G11*I11,2)) | L11: =IF(B11="","",ROUND(K11*'Setup & Guide'!$B$7,2)) | M11: =IF(B11="","",ROUND(K11-(G11*J11),2)) | N11: =IF(B11="","",IFERROR(M11/K11,0)) | O11: =IF(B11="","",E11+F11+H11-G11)
K12: =IF(B12="","",ROUND(G12*I12,2)) | L12: =IF(B12="","",ROUND(K12*'Setup & Guide'!$B$7,2)) | M12: =IF(B12="","",ROUND(K12-(G12*J12),2)) | N12: =IF(B12="","",IFERROR(M12/K12,0)) | O12: =IF(B12="","",E12+F12+H12-G12)
K13: =IF(B13="","",ROUND(G13*I13,2)) | L13: =IF(B13="","",ROUND(K13*'Setup & Guide'!$B$7,2)) | M13: =IF(B13="","",ROUND(K13-(G13*J13),2)) | N13: =IF(B13="","",IFERROR(M13/K13,0)) | O13: =IF(B13="","",E13+F13+H13-G13)
K14: =IF(B14="","",ROUND(G14*I14,2)) | L14: =IF(B14="","",ROUND(K14*'Setup & Guide'!$B$7,2)) | M14: =IF(B14="","",ROUND(K14-(G14*J14),2)) | N14: =IF(B14="","",IFERROR(M14/K14,0)) | O14: =IF(B14="","",E14+F14+H14-G14)
K15: =IF(B15="","",ROUND(G15*I15,2)) | L15: =IF(B15="","",ROUND(K15*'Setup & Guide'!$B$7,2)) | M15: =IF(B15="","",ROUND(K15-(G15*J15),2)) | N15: =IF(B15="","",IFERROR(M15/K15,0)) | O15: =IF(B15="","",E15+F15+H15-G15)
K16: =IF(B16="","",ROUND(G16*I16,2)) | L16: =IF(B16="","",ROUND(K16*'Setup & Guide'!$B$7,2)) | M16: =IF(B16="","",ROUND(K16-(G16*J16),2)) | N16: =IF(B16="","",IFERROR(M16/K16,0)) | O16: =IF(B16="","",E16+F16+H16-G16)
K17: =IF(B17="","",ROUND(G17*I17,2)) | L17: =IF(B17="","",ROUND(K17*'Setup & Guide'!$B$7,2)) | M17: =IF(B17="","",ROUND(K17-(G17*J17),2)) | N17: =IF(B17="","",IFERROR(M17/K17,0)) | O17: =IF(B17="","",E17+F17+H17-G17)
K18: =IF(B18="","",ROUND(G18*I18,2)) | L18: =IF(B18="","",ROUND(K18*'Setup & Guide'!$B$7,2)) | M18: =IF(B18="","",ROUND(K18-(G18*J18),2)) | N18: =IF(B18="","",IFERROR(M18/K18,0)) | O18: =IF(B18="","",E18+F18+H18-G18)
K19: =IF(B19="","",ROUND(G19*I19,2)) | L19: =IF(B19="","",ROUND(K19*'Setup & Guide'!$B$7,2)) | M19: =IF(B19="","",ROUND(K19-(G19*J19),2)) | N19: =IF(B19="","",IFERROR(M19/K19,0)) | O19: =IF(B19="","",E19+F19+H19-G19)
K20: =IF(B20="","",ROUND(G20*I20,2)) | L20: =IF(B20="","",ROUND(K20*'Setup & Guide'!$B$7,2)) | M20: =IF(B20="","",ROUND(K20-(G20*J20),2)) | N20: =IF(B20="","",IFERROR(M20/K20,0)) | O20: =IF(B20="","",E20+F20+H20-G20)
... K55: =IF(B55="","",ROUND(G55*I55,2)) | L55: =IF(B55="","",ROUND(K55*'Setup & Guide'!$B$7,2)) | M55: =IF(B55="","",ROUND(K55-(G55*J55),2)) | N55: =IF(B55="","",IFERROR(M55/K55,0)) | O55: =IF(B55="","",E55+F55+H55-G55)

Sheet Setup & Guide
A1: REPORT CONFIGURATION & SYSTEM GUIDE
A3: Company Name | B3: Rulership LTD PTY
A4: Business Description | B4: 2L Detergent Manufacturing & Retail Sales
A5: Facility / Branch | B5: Sakhile Ext7 Facility
A6: Report Period | B6: 46235
A7: VAT Rate | B7: 0.15
A8: Previous Month Revenue | B8: 123187.3
A9: Template Capacity | B9: 50 product rows per generated report
A11: SYSTEM FIELD MAPPING
A12: Target Cell / Column | B12: System Field | C12: Required | D12: Purpose
A13: Setup & Guide!B3 | B13: company_name | C13: Yes | D13: Company name displayed on the report
A14: Setup & Guide!B4 | B14: business_description | C14: No | D14: Report subtitle
A15: Setup & Guide!B5 | B15: facility | C15: No | D15: Branch or production facility
A16: Setup & Guide!B6 | B16: report_period | C16: Yes | D16: Use an Excel date value
A17: Setup & Guide!B7 | B17: vat_rate | C17: Yes | D17: Decimal rate, for example 0.15
A18: Setup & Guide!B8 | B18: previous_month_revenue | C18: No | D18: Used for the growth KPI
A19: System Data!A6:A55 | B19: sku | C19: No | D19: Unique product code
A20: System Data!B6:B55 | B20: product_name | C20: Yes | D20: Product displayed in the report
A21: System Data!C6:C55 | B21: category | C21: No | D21: Product line or category
A22: System Data!D6:D55 | B22: unit_label | C22: No | D22: Bottle, box, pack, unit, etc.
A23: System Data!E6:E55 | B23: opening_stock | C23: No | D23: Stock at the start of the period
... A27: System Data!I6:J55 | B27: unit_price / unit_cost | C27: Yes | D27: Prices excluding VAT and unit cost
A29: How to use: update the blue configuration cells, write product inputs into System Data columns A:J, keep columns K:O as formulas, then export the Financial Report sheet or the full workbook.

Sheet Checks
A1: MODEL CHECKS
A3: MODEL STATUS | B3: =IF(COUNTIF(B6:B10,"FAIL")=0,"PASS","REVIEW") -> PASS
A5: Check | B5: Status | C5: Delta / Count | D5: Action
A6: Revenue reconciles | B6: =IF(ABS(C6)<0.01,"PASS","FAIL") -> PASS | C6: ='Financial Report'!$A$6-SUM('System Data'!$K$6:$K$55) -> 0 | D6: Report total must equal product revenue
A7: VAT reconciles | B7: =IF(ABS(C7)<0.01,"PASS","FAIL") -> PASS | C7: ='Financial Report'!$C$6-SUM('System Data'!$L$6:$L$55) -> 0 | D7: Report VAT must equal product VAT
A8: Gross margin reconciles | B8: =IF(ABS(C8)<0.01,"PASS","FAIL") -> PASS | C8: ='Financial Report'!$E$6-IFERROR(SUM('System Data'!$M$6:$M$55)/SUM('System Data'!$K$6:$K$55),0) -> 0 | D8: Headline margin must equal weighted product margin
A9: No negative closing stock | B9: =IF(C9=0,"PASS","FAIL") -> PASS | C9: =COUNTIF('System Data'!$O$6:$O$55,"<0") -> 0 | D9: Review opening stock, production, sales, and adjustments
A10: Required product names present | B10: =IF(C10=0,"PASS","FAIL") -> PASS | C10: =COUNTIFS('System Data'!$G$6:$G$55,">0",'System Data'!$B$6:$B$55,"") -> 0 | D10: Every sold item needs a product name
